{
    "key": "group_6311f7eeab879",
    "title": "Stack Animated Carousel",
    "fields": [
        {
            "key": "field_63fbca1f04156",
            "label": "General",
            "name": "",
            "aria-label": "",
            "type": "tab",
            "instructions": "",
            "required": 0,
            "conditional_logic": 0,
            "wrapper": {
                "width": "",
                "class": "",
                "id": ""
            },
            "placement": "top",
            "endpoint": 0
        },
        {
            "key": "field_6311f7f549c32",
            "label": "",
            "name": "conditions",
            "aria-label": "",
            "type": "group",
            "instructions": "",
            "required": 0,
            "conditional_logic": 0,
            "wrapper": {
                "width": "",
                "class": "",
                "id": ""
            },
            "layout": "block",
            "sub_fields": [
                {
                    "key": "field_63fbcd5f29fa9",
                    "label": "Header Conditions",
                    "name": "",
                    "aria-label": "",
                    "type": "tab",
                    "instructions": "",
                    "required": 0,
                    "conditional_logic": 0,
                    "wrapper": {
                        "width": "",
                        "class": "",
                        "id": ""
                    },
                    "placement": "top",
                    "endpoint": 0
                },
                {
                    "key": "field_6311f82c49c33",
                    "label": "Has Header",
                    "name": "has_title",
                    "aria-label": "",
                    "type": "true_false",
                    "instructions": "",
                    "required": 0,
                    "conditional_logic": 0,
                    "wrapper": {
                        "width": "25",
                        "class": "",
                        "id": ""
                    },
                    "message": "",
                    "default_value": 0,
                    "ui_on_text": "",
                    "ui_off_text": "",
                    "ui": 1
                },
                {
                    "key": "field_63fbcd4b29fa8",
                    "label": "Card Conditions",
                    "name": "",
                    "aria-label": "",
                    "type": "tab",
                    "instructions": "",
                    "required": 0,
                    "conditional_logic": 0,
                    "wrapper": {
                        "width": "",
                        "class": "",
                        "id": ""
                    },
                    "placement": "top",
                    "endpoint": 0
                },
                {
                    "key": "field_633dedef35d7d",
                    "label": "Has Workshop Sync",
                    "name": "is_workshop",
                    "aria-label": "",
                    "type": "true_false",
                    "instructions": "",
                    "required": 0,
                    "conditional_logic": 0,
                    "wrapper": {
                        "width": "25",
                        "class": "",
                        "id": ""
                    },
                    "message": "",
                    "default_value": 0,
                    "ui_on_text": "",
                    "ui_off_text": "",
                    "ui": 1
                },
                {
                    "key": "field_6311f87f49c34",
                    "label": "Has Images",
                    "name": "has_images",
                    "aria-label": "",
                    "type": "true_false",
                    "instructions": "",
                    "required": 0,
                    "conditional_logic": 0,
                    "wrapper": {
                        "width": "25",
                        "class": "",
                        "id": ""
                    },
                    "message": "",
                    "default_value": 0,
                    "ui_on_text": "",
                    "ui_off_text": "",
                    "ui": 1
                },
                {
                    "key": "field_6311f8ab49c35",
                    "label": "Has Author",
                    "name": "has_author_field",
                    "aria-label": "",
                    "type": "true_false",
                    "instructions": "",
                    "required": 0,
                    "conditional_logic": 0,
                    "wrapper": {
                        "width": "25",
                        "class": "",
                        "id": ""
                    },
                    "message": "",
                    "default_value": 0,
                    "ui_on_text": "",
                    "ui_off_text": "",
                    "ui": 1
                },
                {
                    "key": "field_6311f8d549c36",
                    "label": "Has CTA",
                    "name": "has_ctas",
                    "aria-label": "",
                    "type": "true_false",
                    "instructions": "",
                    "required": 0,
                    "conditional_logic": 0,
                    "wrapper": {
                        "width": "25",
                        "class": "",
                        "id": ""
                    },
                    "message": "",
                    "default_value": 0,
                    "ui_on_text": "",
                    "ui_off_text": "",
                    "ui": 1
                },
                {
                    "key": "field_63fc19643eceb",
                    "label": "Has Time",
                    "name": "has_time",
                    "aria-label": "",
                    "type": "true_false",
                    "instructions": "",
                    "required": 0,
                    "conditional_logic": [
                        [
                            {
                                "field": "field_633dedef35d7d",
                                "operator": "==",
                                "value": "1"
                            }
                        ]
                    ],
                    "wrapper": {
                        "width": "25",
                        "class": "",
                        "id": ""
                    },
                    "message": "",
                    "default_value": 0,
                    "ui_on_text": "",
                    "ui_off_text": "",
                    "ui": 1
                }
            ]
        },
        {
            "key": "field_63fbcf99d5684",
            "label": "Header",
            "name": "",
            "aria-label": "",
            "type": "tab",
            "instructions": "",
            "required": 0,
            "conditional_logic": [
                [
                    {
                        "field": "field_6311f82c49c33",
                        "operator": "==",
                        "value": "1"
                    }
                ]
            ],
            "wrapper": {
                "width": "",
                "class": "",
                "id": ""
            },
            "placement": "top",
            "endpoint": 1
        },
        {
            "key": "field_63fbcf99d5684",
            "label": "Header",
            "name": "",
            "aria-label": "",
            "type": "tab",
            "instructions": "",
            "required": 0,
            "conditional_logic": [
                [
                    {
                        "field": "field_6311f82c49c33",
                        "operator": "==",
                        "value": "1"
                    }
                ]
            ],
            "wrapper": {
                "width": "",
                "class": "",
                "id": ""
            },
            "placement": "top",
            "endpoint": 1
        },
        {
            "key": "field_6311f9eb49c38",
            "label": "Header",
            "name": "header",
            "aria-label": "",
            "type": "group",
            "instructions": "",
            "required": 0,
            "conditional_logic": [
                [
                    {
                        "field": "field_6311f82c49c33",
                        "operator": "==",
                        "value": "1"
                    }
                ]
            ],
            "wrapper": {
                "width": "",
                "class": "",
                "id": ""
            },
            "layout": "block",
            "sub_fields": [
                {
                    "key": "field_6311fa0749c39",
                    "label": "Header fields",
                    "name": "header_clone",
                    "aria-label": "",
                    "type": "clone",
                    "instructions": "",
                    "required": 0,
                    "conditional_logic": 0,
                    "wrapper": {
                        "width": "",
                        "class": "",
                        "id": ""
                    },
                    "clone": [
                        "field_6307e14f19e24",
                        "field_62f69cd86fb45",
                        "field_62ffaf73f0ba2",
                        "field_62ffb21e9fdab",
                        "field_62fc05e4832eb",
                        "field_62f6bd93217fe"
                    ],
                    "display": "seamless",
                    "layout": "block",
                    "prefix_label": 0,
                    "prefix_name": 0
                }
            ]
        },
        {
            "key": "field_63fbca0704155",
            "label": "Cards",
            "name": "",
            "aria-label": "",
            "type": "tab",
            "instructions": "",
            "required": 0,
            "conditional_logic": 0,
            "wrapper": {
                "width": "",
                "class": "",
                "id": ""
            },
            "placement": "top",
            "endpoint": 0
        },
        {
            "key": "field_63fbca0704155",
            "label": "Cards",
            "name": "",
            "aria-label": "",
            "type": "tab",
            "instructions": "",
            "required": 0,
            "conditional_logic": 0,
            "wrapper": {
                "width": "",
                "class": "",
                "id": ""
            },
            "placement": "top",
            "endpoint": 0
        },
        {
            "key": "field_6311f98c49c37",
            "label": "Carousel Position",
            "name": "carousel_position",
            "aria-label": "",
            "type": "select",
            "instructions": "",
            "required": 0,
            "conditional_logic": 0,
            "wrapper": {
                "width": "100",
                "class": "",
                "id": ""
            },
            "choices": {
                "left": "Left",
                "right": "Right"
            },
            "default_value": "right",
            "return_format": "value",
            "multiple": 0,
            "allow_null": 0,
            "ui": 1,
            "ajax": 0,
            "placeholder": ""
        },
        {
            "key": "field_6311faab49c3a",
            "label": "Cards",
            "name": "cards",
            "aria-label": "",
            "type": "repeater",
            "instructions": "",
            "required": 0,
            "conditional_logic": 0,
            "wrapper": {
                "width": "",
                "class": "",
                "id": ""
            },
            "layout": "block",
            "pagination": 0,
            "min": 1,
            "max": 0,
            "collapsed": "field_6311fb5749c3d",
            "button_label": "Add Card",
            "rows_per_page": 20,
            "sub_fields": [
                {
                    "key": "field_63fbd1d0345bf",
                    "label": "Image",
                    "name": "",
                    "aria-label": "",
                    "type": "tab",
                    "instructions": "",
                    "required": 0,
                    "conditional_logic": [
                        [
                            {
                                "field": "field_6311f87f49c34",
                                "operator": "==",
                                "value": "1"
                            },
                            {
                                "field": "field_633dedef35d7d",
                                "operator": "!=",
                                "value": "1"
                            }
                        ]
                    ],
                    "wrapper": {
                        "width": "",
                        "class": "",
                        "id": ""
                    },
                    "placement": "top",
                    "endpoint": 0,
                    "parent_repeater": "field_6311faab49c3a"
                },
                {
                    "key": "field_63fbd1d0345bf",
                    "label": "Image",
                    "name": "",
                    "aria-label": "",
                    "type": "tab",
                    "instructions": "",
                    "required": 0,
                    "conditional_logic": [
                        [
                            {
                                "field": "field_6311f87f49c34",
                                "operator": "==",
                                "value": "1"
                            },
                            {
                                "field": "field_633dedef35d7d",
                                "operator": "!=",
                                "value": "1"
                            }
                        ]
                    ],
                    "wrapper": {
                        "width": "",
                        "class": "",
                        "id": ""
                    },
                    "placement": "top",
                    "endpoint": 0,
                    "parent_repeater": "field_6311faab49c3a"
                },
                {
                    "key": "field_6311fb2149c3c",
                    "label": "Image",
                    "name": "card_image",
                    "aria-label": "",
                    "type": "image",
                    "instructions": "",
                    "required": 0,
                    "conditional_logic": [
                        [
                            {
                                "field": "field_6311f87f49c34",
                                "operator": "==",
                                "value": "1"
                            },
                            {
                                "field": "field_633dedef35d7d",
                                "operator": "!=",
                                "value": "1"
                            }
                        ]
                    ],
                    "wrapper": {
                        "width": "50",
                        "class": "",
                        "id": ""
                    },
                    "return_format": "array",
                    "library": "all",
                    "min_width": "",
                    "min_height": "",
                    "min_size": "",
                    "max_width": "",
                    "max_height": "",
                    "max_size": "",
                    "mime_types": "",
                    "preview_size": "medium",
                    "parent_repeater": "field_6311faab49c3a"
                },
                {
                    "key": "field_6311fad549c3b",
                    "label": "Image Position",
                    "name": "image_position",
                    "aria-label": "",
                    "type": "radio",
                    "instructions": "",
                    "required": 0,
                    "conditional_logic": [
                        [
                            {
                                "field": "field_6311f87f49c34",
                                "operator": "==",
                                "value": "1"
                            },
                            {
                                "field": "field_633dedef35d7d",
                                "operator": "!=",
                                "value": "1"
                            }
                        ]
                    ],
                    "wrapper": {
                        "width": "50",
                        "class": "",
                        "id": ""
                    },
                    "choices": {
                        "top": "Top (Used for logos)",
                        "left": "Left (Uses for Profile Picture)"
                    },
                    "default_value": "top",
                    "return_format": "value",
                    "allow_null": 0,
                    "other_choice": 0,
                    "layout": "horizontal",
                    "save_other_choice": 0,
                    "parent_repeater": "field_6311faab49c3a"
                },
                {
                    "key": "field_63fbd2552edb4",
                    "label": "Workshop Sync",
                    "name": "",
                    "aria-label": "",
                    "type": "tab",
                    "instructions": "",
                    "required": 0,
                    "conditional_logic": [
                        [
                            {
                                "field": "field_633dedef35d7d",
                                "operator": "==",
                                "value": "1"
                            }
                        ]
                    ],
                    "wrapper": {
                        "width": "",
                        "class": "",
                        "id": ""
                    },
                    "placement": "top",
                    "endpoint": 0,
                    "parent_repeater": "field_6311faab49c3a"
                },
                {
                    "key": "field_63fbd2552edb4",
                    "label": "Workshop Sync",
                    "name": "",
                    "aria-label": "",
                    "type": "tab",
                    "instructions": "",
                    "required": 0,
                    "conditional_logic": [
                        [
                            {
                                "field": "field_633dedef35d7d",
                                "operator": "==",
                                "value": "1"
                            }
                        ]
                    ],
                    "wrapper": {
                        "width": "",
                        "class": "",
                        "id": ""
                    },
                    "placement": "top",
                    "endpoint": 0,
                    "parent_repeater": "field_6311faab49c3a"
                },
                {
                    "key": "field_633dee8e6fa03",
                    "label": "Workshop Sync",
                    "name": "workshop",
                    "aria-label": "",
                    "type": "post_object",
                    "instructions": "",
                    "required": 1,
                    "conditional_logic": [
                        [
                            {
                                "field": "field_633dedef35d7d",
                                "operator": "==",
                                "value": "1"
                            }
                        ]
                    ],
                    "wrapper": {
                        "width": "",
                        "class": "",
                        "id": ""
                    },
                    "post_type": [
                        "workshops"
                    ],
                    "taxonomy": "",
                    "return_format": "object",
                    "multiple": 0,
                    "allow_null": 0,
                    "ui": 1,
                    "parent_repeater": "field_6311faab49c3a"
                },
                {
                    "key": "field_63fbd1db345c0",
                    "label": "Copy",
                    "name": "",
                    "aria-label": "",
                    "type": "tab",
                    "instructions": "",
                    "required": 0,
                    "conditional_logic": [
                        [
                            {
                                "field": "field_633dedef35d7d",
                                "operator": "!=",
                                "value": "1"
                            }
                        ]
                    ],
                    "wrapper": {
                        "width": "",
                        "class": "",
                        "id": ""
                    },
                    "placement": "top",
                    "endpoint": 0,
                    "parent_repeater": "field_6311faab49c3a"
                },
                {
                    "key": "field_63fbd1db345c0",
                    "label": "Copy",
                    "name": "",
                    "aria-label": "",
                    "type": "tab",
                    "instructions": "",
                    "required": 0,
                    "conditional_logic": [
                        [
                            {
                                "field": "field_633dedef35d7d",
                                "operator": "!=",
                                "value": "1"
                            }
                        ]
                    ],
                    "wrapper": {
                        "width": "",
                        "class": "",
                        "id": ""
                    },
                    "placement": "top",
                    "endpoint": 0,
                    "parent_repeater": "field_6311faab49c3a"
                },
                {
                    "key": "field_6311fb5749c3d",
                    "label": "Primary Copy",
                    "name": "content",
                    "aria-label": "",
                    "type": "textarea",
                    "instructions": "",
                    "required": 1,
                    "conditional_logic": [
                        [
                            {
                                "field": "field_633dedef35d7d",
                                "operator": "!=",
                                "value": "1"
                            }
                        ]
                    ],
                    "wrapper": {
                        "width": "50",
                        "class": "",
                        "id": ""
                    },
                    "default_value": "",
                    "maxlength": "",
                    "rows": 4,
                    "placeholder": "",
                    "new_lines": "",
                    "parent_repeater": "field_6311faab49c3a"
                },
                {
                    "key": "field_63fbd3787a403",
                    "label": "Secondary Copy (Optional)",
                    "name": "content_secondary",
                    "aria-label": "",
                    "type": "textarea",
                    "instructions": "",
                    "required": 0,
                    "conditional_logic": [
                        [
                            {
                                "field": "field_633dedef35d7d",
                                "operator": "!=",
                                "value": "1"
                            }
                        ]
                    ],
                    "wrapper": {
                        "width": "50",
                        "class": "",
                        "id": ""
                    },
                    "default_value": "",
                    "maxlength": "",
                    "rows": 4,
                    "placeholder": "",
                    "new_lines": "",
                    "parent_repeater": "field_6311faab49c3a"
                },
                {
                    "key": "field_63fbd3787a403",
                    "label": "Secondary Copy (Optional)",
                    "name": "content_secondary",
                    "aria-label": "",
                    "type": "textarea",
                    "instructions": "",
                    "required": 0,
                    "conditional_logic": [
                        [
                            {
                                "field": "field_633dedef35d7d",
                                "operator": "!=",
                                "value": "1"
                            }
                        ]
                    ],
                    "wrapper": {
                        "width": "50",
                        "class": "",
                        "id": ""
                    },
                    "default_value": "",
                    "maxlength": "",
                    "rows": 4,
                    "placeholder": "",
                    "new_lines": "",
                    "parent_repeater": "field_6311faab49c3a"
                },
                {
                    "key": "field_63fbd1ff345c1",
                    "label": "Author",
                    "name": "",
                    "aria-label": "",
                    "type": "tab",
                    "instructions": "",
                    "required": 0,
                    "conditional_logic": [
                        [
                            {
                                "field": "field_6311f8ab49c35",
                                "operator": "==",
                                "value": "1"
                            }
                        ]
                    ],
                    "wrapper": {
                        "width": "",
                        "class": "",
                        "id": ""
                    },
                    "placement": "top",
                    "endpoint": 0,
                    "parent_repeater": "field_6311faab49c3a"
                },
                {
                    "key": "field_63fbd1ff345c1",
                    "label": "Author",
                    "name": "",
                    "aria-label": "",
                    "type": "tab",
                    "instructions": "",
                    "required": 0,
                    "conditional_logic": [
                        [
                            {
                                "field": "field_6311f8ab49c35",
                                "operator": "==",
                                "value": "1"
                            }
                        ]
                    ],
                    "wrapper": {
                        "width": "",
                        "class": "",
                        "id": ""
                    },
                    "placement": "top",
                    "endpoint": 0,
                    "parent_repeater": "field_6311faab49c3a"
                },
                {
                    "key": "field_6311fb7949c3e",
                    "label": "Author",
                    "name": "author",
                    "aria-label": "",
                    "type": "group",
                    "instructions": "",
                    "required": 0,
                    "conditional_logic": [
                        [
                            {
                                "field": "field_6311f8ab49c35",
                                "operator": "==",
                                "value": "1"
                            }
                        ]
                    ],
                    "wrapper": {
                        "width": "",
                        "class": "",
                        "id": ""
                    },
                    "layout": "block",
                    "parent_repeater": "field_6311faab49c3a",
                    "sub_fields": [
                        {
                            "key": "field_6311fba349c3f",
                            "label": "Name",
                            "name": "name",
                            "aria-label": "",
                            "type": "text",
                            "instructions": "",
                            "required": 1,
                            "conditional_logic": 0,
                            "wrapper": {
                                "width": "33",
                                "class": "",
                                "id": ""
                            },
                            "default_value": "",
                            "placeholder": "",
                            "prepend": "",
                            "append": "",
                            "maxlength": ""
                        },
                        {
                            "key": "field_6311fbc249c40",
                            "label": "Job Title",
                            "name": "job_title",
                            "aria-label": "",
                            "type": "text",
                            "instructions": "",
                            "required": 0,
                            "conditional_logic": 0,
                            "wrapper": {
                                "width": "33",
                                "class": "",
                                "id": ""
                            },
                            "default_value": "",
                            "placeholder": "",
                            "prepend": "",
                            "append": "",
                            "maxlength": ""
                        },
                        {
                            "key": "field_6311fbdb49c41",
                            "label": "Location",
                            "name": "location",
                            "aria-label": "",
                            "type": "text",
                            "instructions": "",
                            "required": 0,
                            "conditional_logic": 0,
                            "wrapper": {
                                "width": "33",
                                "class": "",
                                "id": ""
                            },
                            "default_value": "",
                            "placeholder": "",
                            "prepend": "",
                            "append": "",
                            "maxlength": ""
                        }
                    ]
                },
                {
                    "key": "field_63fbd20b345c2",
                    "label": "CTA",
                    "name": "",
                    "aria-label": "",
                    "type": "tab",
                    "instructions": "",
                    "required": 0,
                    "conditional_logic": [
                        [
                            {
                                "field": "field_6311f8d549c36",
                                "operator": "==",
                                "value": "1"
                            }
                        ]
                    ],
                    "wrapper": {
                        "width": "",
                        "class": "",
                        "id": ""
                    },
                    "placement": "top",
                    "endpoint": 0,
                    "parent_repeater": "field_6311faab49c3a"
                },
                {
                    "key": "field_63fbd20b345c2",
                    "label": "CTA",
                    "name": "",
                    "aria-label": "",
                    "type": "tab",
                    "instructions": "",
                    "required": 0,
                    "conditional_logic": [
                        [
                            {
                                "field": "field_6311f8d549c36",
                                "operator": "==",
                                "value": "1"
                            }
                        ]
                    ],
                    "wrapper": {
                        "width": "",
                        "class": "",
                        "id": ""
                    },
                    "placement": "top",
                    "endpoint": 0,
                    "parent_repeater": "field_6311faab49c3a"
                },
                {
                    "key": "field_63fbd20b345c2",
                    "label": "CTA",
                    "name": "",
                    "aria-label": "",
                    "type": "tab",
                    "instructions": "",
                    "required": 0,
                    "conditional_logic": [
                        [
                            {
                                "field": "field_6311f8d549c36",
                                "operator": "==",
                                "value": "1"
                            }
                        ]
                    ],
                    "wrapper": {
                        "width": "",
                        "class": "",
                        "id": ""
                    },
                    "placement": "top",
                    "endpoint": 0,
                    "parent_repeater": "field_6311faab49c3a"
                },
                {
                    "key": "field_6311fbfc49c42",
                    "label": "CTA",
                    "name": "cta_field",
                    "aria-label": "",
                    "type": "group",
                    "instructions": "Recommended Button Type: 'Secondary Dark'",
                    "required": 0,
                    "conditional_logic": [
                        [
                            {
                                "field": "field_6311f8d549c36",
                                "operator": "==",
                                "value": "1"
                            }
                        ]
                    ],
                    "wrapper": {
                        "width": "",
                        "class": "",
                        "id": ""
                    },
                    "layout": "block",
                    "parent_repeater": "field_6311faab49c3a",
                    "sub_fields": [
                        {
                            "key": "field_6311fc1e49c43",
                            "label": "CTA",
                            "name": "cta",
                            "aria-label": "",
                            "type": "clone",
                            "instructions": "",
                            "required": 0,
                            "conditional_logic": 0,
                            "wrapper": {
                                "width": "",
                                "class": "",
                                "id": ""
                            },
                            "clone": [
                                "group_62f411801a10c"
                            ],
                            "display": "seamless",
                            "layout": "block",
                            "prefix_label": 0,
                            "prefix_name": 0
                        }
                    ]
                },
                {
                    "key": "field_63fc1caaab353",
                    "label": "Styles and Attributes",
                    "name": "",
                    "aria-label": "",
                    "type": "tab",
                    "instructions": "",
                    "required": 0,
                    "conditional_logic": 0,
                    "wrapper": {
                        "width": "",
                        "class": "",
                        "id": ""
                    },
                    "placement": "top",
                    "endpoint": 0,
                    "parent_repeater": "field_6311faab49c3a"
                },
                {
                    "key": "field_63fc1caaab353",
                    "label": "Styles and Attributes",
                    "name": "",
                    "aria-label": "",
                    "type": "tab",
                    "instructions": "",
                    "required": 0,
                    "conditional_logic": 0,
                    "wrapper": {
                        "width": "",
                        "class": "",
                        "id": ""
                    },
                    "placement": "top",
                    "endpoint": 0,
                    "parent_repeater": "field_6311faab49c3a"
                },
                {
                    "key": "field_63fc1caaab353",
                    "label": "Styles and Attributes",
                    "name": "",
                    "aria-label": "",
                    "type": "tab",
                    "instructions": "",
                    "required": 0,
                    "conditional_logic": 0,
                    "wrapper": {
                        "width": "",
                        "class": "",
                        "id": ""
                    },
                    "placement": "top",
                    "endpoint": 0,
                    "parent_repeater": "field_6311faab49c3a"
                },
                {
                    "key": "field_63fc1ce6ab354",
                    "label": "Styles",
                    "name": "styles",
                    "aria-label": "",
                    "type": "group",
                    "instructions": "",
                    "required": 0,
                    "conditional_logic": 0,
                    "wrapper": {
                        "width": "",
                        "class": "",
                        "id": ""
                    },
                    "layout": "block",
                    "parent_repeater": "field_6311faab49c3a",
                    "sub_fields": [
                        {
                            "key": "field_63fc1ff46f8f1",
                            "label": "Override Background Color",
                            "name": "override_background_color",
                            "aria-label": "",
                            "type": "true_false",
                            "instructions": "",
                            "required": 0,
                            "conditional_logic": 0,
                            "wrapper": {
                                "width": "50",
                                "class": "",
                                "id": ""
                            },
                            "message": "",
                            "default_value": 0,
                            "ui_on_text": "Yes",
                            "ui_off_text": "No",
                            "ui": 1
                        },
                        {
                            "key": "field_63fc1cf2ab355",
                            "label": "Background Color",
                            "name": "background_color",
                            "aria-label": "",
                            "type": "select",
                            "instructions": "",
                            "required": 0,
                            "conditional_logic": [
                                [
                                    {
                                        "field": "field_63fc1ff46f8f1",
                                        "operator": "==",
                                        "value": "1"
                                    }
                                ]
                            ],
                            "wrapper": {
                                "width": "50",
                                "class": "",
                                "id": ""
                            },
                            "choices": {
                                "bg-teal-dark": "Teal Dark",
                                "bg-wine-dark": "Wine Dark"
                            },
                            "default_value": "bg-teal-dark",
                            "return_format": "value",
                            "multiple": 0,
                            "allow_null": 0,
                            "ui": 1,
                            "ajax": 0,
                            "placeholder": ""
                        }
                    ]
                },
                {
                    "key": "field_63fc1ce6ab354",
                    "label": "Styles",
                    "name": "styles",
                    "aria-label": "",
                    "type": "group",
                    "instructions": "",
                    "required": 0,
                    "conditional_logic": 0,
                    "wrapper": {
                        "width": "",
                        "class": "",
                        "id": ""
                    },
                    "layout": "block",
                    "parent_repeater": "field_6311faab49c3a",
                    "sub_fields": [
                        {
                            "key": "field_63fc1ff46f8f1",
                            "label": "Override Background Color",
                            "name": "override_background_color",
                            "aria-label": "",
                            "type": "true_false",
                            "instructions": "",
                            "required": 0,
                            "conditional_logic": 0,
                            "wrapper": {
                                "width": "50",
                                "class": "",
                                "id": ""
                            },
                            "message": "",
                            "default_value": 0,
                            "ui_on_text": "Yes",
                            "ui_off_text": "No",
                            "ui": 1
                        },
                        {
                            "key": "field_63fc1cf2ab355",
                            "label": "Background Color",
                            "name": "background_color",
                            "aria-label": "",
                            "type": "select",
                            "instructions": "",
                            "required": 0,
                            "conditional_logic": [
                                [
                                    {
                                        "field": "field_63fc1ff46f8f1",
                                        "operator": "==",
                                        "value": "1"
                                    }
                                ]
                            ],
                            "wrapper": {
                                "width": "50",
                                "class": "",
                                "id": ""
                            },
                            "choices": {
                                "bg-teal-dark": "Teal Dark",
                                "bg-wine-dark": "Wine Dark"
                            },
                            "default_value": "bg-teal-dark",
                            "return_format": "value",
                            "multiple": 0,
                            "allow_null": 0,
                            "ui": 1,
                            "ajax": 0,
                            "placeholder": ""
                        }
                    ]
                },
                {
                    "key": "field_63fc1ce6ab354",
                    "label": "Styles",
                    "name": "styles",
                    "aria-label": "",
                    "type": "group",
                    "instructions": "",
                    "required": 0,
                    "conditional_logic": 0,
                    "wrapper": {
                        "width": "",
                        "class": "",
                        "id": ""
                    },
                    "layout": "block",
                    "parent_repeater": "field_6311faab49c3a",
                    "sub_fields": [
                        {
                            "key": "field_63fc1ff46f8f1",
                            "label": "Override Background Color",
                            "name": "override_background_color",
                            "aria-label": "",
                            "type": "true_false",
                            "instructions": "",
                            "required": 0,
                            "conditional_logic": 0,
                            "wrapper": {
                                "width": "50",
                                "class": "",
                                "id": ""
                            },
                            "message": "",
                            "default_value": 0,
                            "ui_on_text": "Yes",
                            "ui_off_text": "No",
                            "ui": 1
                        },
                        {
                            "key": "field_63fc1cf2ab355",
                            "label": "Background Color",
                            "name": "background_color",
                            "aria-label": "",
                            "type": "select",
                            "instructions": "",
                            "required": 0,
                            "conditional_logic": [
                                [
                                    {
                                        "field": "field_63fc1ff46f8f1",
                                        "operator": "==",
                                        "value": "1"
                                    }
                                ]
                            ],
                            "wrapper": {
                                "width": "50",
                                "class": "",
                                "id": ""
                            },
                            "choices": {
                                "bg-teal-dark": "Teal Dark",
                                "bg-wine-dark": "Wine Dark"
                            },
                            "default_value": "bg-teal-dark",
                            "return_format": "value",
                            "multiple": 0,
                            "allow_null": 0,
                            "ui": 1,
                            "ajax": 0,
                            "placeholder": ""
                        }
                    ]
                }
            ]
        }
    ],
    "location": [
        [
            {
                "param": "options_page",
                "operator": "==",
                "value": "acf-components"
            }
        ]
    ],
    "menu_order": 0,
    "position": "normal",
    "style": "default",
    "label_placement": "top",
    "instruction_placement": "label",
    "hide_on_screen": "",
    "active": true,
    "description": "",
    "show_in_rest": 0,
    "modified": 1686247559
}